<!-- This model was created online using SPLOT's Feature Model Editor (http://www.splot-research.org) on Fri, Jan 1, 2010 - 2:25 PM  -->
<feature_model name="Mobile">
<meta>
<data name="description">Mobile Nokia </data>
<data name="creator">Raian</data>
<data name="address"></data>
<data name="email">raian.ali@gmail.com</data>
<data name="phone"></data>
<data name="website"></data>
<data name="organization">DISI, Unitn</data>
<data name="department"></data>
<data name="date"></data>
<data name="reference"></data>
</meta>
<feature_tree>
:r Mobile Phone(_r)
</feature_tree>
<constraints>
</constraints>
</feature_model>
