<!-- This model was created online using SPLOT's Feature Model Editor (http://www.splot-research.org) on Thu, Jan 7, 2010 - 7:07 AM  -->
<feature_model name="Type name for root feature">
<meta>
<data name="description"></data>
<data name="creator"></data>
<data name="address"></data>
<data name="email"></data>
<data name="phone"></data>
<data name="website"></data>
<data name="organization"></data>
<data name="department"></data>
<data name="date"></data>
<data name="reference"></data>
</meta>
<feature_tree>
:r Type name for root feature(_r)
</feature_tree>
<constraints>
</constraints>
</feature_model>
